lazyros/__init__.py
lazyros/lazyros.css
lazyros/lazyros.py
lazyros/utils/__init__.py
lazyros/utils/custom_widgets.py
lazyros/utils/ignore_parser.py
lazyros/utils/utility.py
lazyros/widgets/__init__.py
lazyros/widgets/node/__init__.py
lazyros/widgets/node/node_info.py
lazyros/widgets/node/node_lifecycle.py
lazyros/widgets/node/node_list.py
lazyros/widgets/node/node_log.py
lazyros/widgets/parameter/__init__.py
lazyros/widgets/parameter/parameter_info.py
lazyros/widgets/parameter/parameter_list.py
lazyros/widgets/parameter/parameter_value.py
lazyros/widgets/topic/__init__.py
lazyros/widgets/topic/topic_echo.py
lazyros/widgets/topic/topic_info.py
lazyros/widgets/topic/topic_list.py
lazyros-0.1.9.5.dist-info/LICENSE
lazyros-0.1.9.5.dist-info/METADATA
lazyros-0.1.9.5.dist-info/WHEEL
lazyros-0.1.9.5.dist-info/entry_points.txt
lazyros-0.1.9.5.dist-info/RECORD
