Metadata-Version: 2.3
Name: lazyros
Version: 0.1.9.5
Summary: 
License: Apache-2.0
Keywords: lazyros,ros2,textual,cli,terminal
Author: Harumo Sasatake
Author-email: sasatake.harumo@techmagic.co.jp
Requires-Python: >=3.10,<4.0.0
Classifier: License :: OSI Approved :: Apache Software License
Classifier: Programming Language :: Python :: 3
Classifier: Programming Language :: Python :: 3.10
Classifier: Programming Language :: Python :: 3.11
Classifier: Programming Language :: Python :: 3.12
Classifier: Programming Language :: Python :: 3.13
Requires-Dist: numpy
Requires-Dist: pyyaml (>=6.0.2,<7.0.0)
Requires-Dist: textual (>=3.5.0,<4.0.0)
Project-URL: Repository, https://github.com/TechMagicKK/lazyros
